ai_helper_agent/__init__.py
ai_helper_agent/cli/__init__.py
ai_helper_agent/cli/cli.py
ai_helper_agent/cli/cli_internet_single.py
ai_helper_agent/cli/cli_selector.py
ai_helper_agent/cli/cli_single.py
ai_helper_agent/cli/enhanced_cli.py
ai_helper_agent/cli/enhanced_internet_cli.py
ai_helper_agent/cli/fast_cli_selector.py
ai_helper_agent/cli/multi_provider_cli.py
ai_helper_agent/cli/multi_provider_startup.py
ai_helper_agent/cli/startup.py
ai_helper_agent/core/__init__.py
ai_helper_agent/core/config.py
ai_helper_agent/core/core.py
ai_helper_agent/core/security.py
ai_helper_agent/core/system_config.py
ai_helper_agent/managers/__init__.py
ai_helper_agent/managers/api_key_manager.py
ai_helper_agent/managers/conversation_manager.py
ai_helper_agent/managers/user_manager.py
ai_helper_agent/providers/__init__.py
ai_helper_agent/utilities/__init__.py
ai_helper_agent/utilities/api_key_setup.py
ai_helper_agent/utilities/simple_logo.py
ai_helper_agent/utils/__init__.py
ai_helper_agent/utils/api_key_helper.py
ai_helper_agent/utils/browser_integration.py
ai_helper_agent/utils/file_handler.py
ai_helper_agent/utils/file_operations.py
ai_helper_agent/utils/internet_access.py
ai_helper_agent/utils/mcp_integration.py
ai_helper_agent/utils/prompt_enhancer.py
ai_helper_agent/utils/rich_formatting.py
ai_helper_agent/utils/secure_cache.py
ai_helper_agent/utils/simple_logo.py
ai_helper_agent/utils/streaming.py
ai_helper_agent/utils/utils.py
ai_helper_agent-2.0.1.dist-info/licenses/LICENSE
ai_helper_agent-2.0.1.dist-info/METADATA
ai_helper_agent-2.0.1.dist-info/WHEEL
ai_helper_agent-2.0.1.dist-info/entry_points.txt
ai_helper_agent-2.0.1.dist-info/top_level.txt
ai_helper_agent-2.0.1.dist-info/RECORD
