Metadata-Version: 2.4
Name: ai-helper-agent
Version: 2.0.1
Summary: Advanced AI-Powered Programming Assistant with Multi-Provider Support, Internet Search, and 40+ CLI Commands
Home-page: https://github.com/AIMLDev726/ai-helper-agent
Author: Meet Solanki (AIML Student)
Author-email: "Meet Solanki (AIML Student)" <aistudentlearn4@gmail.com>
Maintainer-email: AIMLDev726 <aistudentlearn4@gmail.com>
License: MIT
Project-URL: Homepage, https://github.com/AIMLDev726/ai-helper-agent
Project-URL: Documentation, https://github.com/AIMLDev726/ai-helper-agent#readme
Project-URL: Repository, https://github.com/AIMLDev726/ai-helper-agent
Project-URL: Bug Tracker, https://github.com/AIMLDev726/ai-helper-agent/issues
Project-URL: Changelog, https://github.com/AIMLDev726/ai-helper-agent/blob/main/CHANGELOG.md
Keywords: ai,assistant,programming,code-analysis,bug-fixing,automation,groq,openai,anthropic,google,langchain,internet-search,cli,developer-tools,ai-agent
Platform: any
Classifier: Development Status :: 5 - Production/Stable
Classifier: Intended Audience :: Developers
Classifier: Intended Audience :: Education
Classifier: Topic :: Software Development :: Libraries :: Python Modules
Classifier: Topic :: Software Development :: Quality Assurance
Classifier: Topic :: Scientific/Engineering :: Artificial Intelligence
Classifier: Topic :: Internet :: WWW/HTTP :: Indexing/Search
Classifier: Programming Language :: Python :: 3
Classifier: Programming Language :: Python :: 3.8
Classifier: Programming Language :: Python :: 3.9
Classifier: Programming Language :: Python :: 3.10
Classifier: Programming Language :: Python :: 3.11
Classifier: Programming Language :: Python :: 3.12
Classifier: License :: OSI Approved :: MIT License
Classifier: Operating System :: OS Independent
Classifier: Operating System :: Microsoft :: Windows
Classifier: Operating System :: POSIX :: Linux
Classifier: Operating System :: MacOS
Requires-Python: >=3.8
License-File: LICENSE
Requires-Dist: langchain>=0.1.0
Requires-Dist: langchain-core>=0.1.0
Requires-Dist: langchain-community>=0.1.0
Requires-Dist: langchain-groq>=0.1.0
Requires-Dist: langchain-openai>=0.1.0
Requires-Dist: langchain-anthropic>=0.1.0
Requires-Dist: langchain-google-genai>=0.1.0
Requires-Dist: langchain-ollama>=0.1.0
Requires-Dist: rich>=13.0.0
Requires-Dist: structlog>=23.0.0
Requires-Dist: requests>=2.25.0
Requires-Dist: cryptography>=3.4.0
Requires-Dist: sqlalchemy>=1.4.0
Requires-Dist: beautifulsoup4>=4.9.0
Requires-Dist: duckduckgo-search>=3.0.0
Requires-Dist: googlesearch-python>=1.2.0
Requires-Dist: faiss-cpu>=1.7.0
Requires-Dist: chromadb>=0.4.0
Requires-Dist: pathlib2; python_version < "3.4"
Provides-Extra: dev
Requires-Dist: pytest>=6.0; extra == "dev"
Requires-Dist: pytest-cov; extra == "dev"
Requires-Dist: black; extra == "dev"
Requires-Dist: flake8; extra == "dev"
Requires-Dist: mypy; extra == "dev"
Requires-Dist: pre-commit; extra == "dev"
Provides-Extra: test
Requires-Dist: pytest>=6.0; extra == "test"
Requires-Dist: pytest-cov; extra == "test"
Dynamic: author
Dynamic: home-page
Dynamic: license-file
Dynamic: platform
Dynamic: requires-python
